Workbook

Sheet Supuestos
A1: QUORELIA · MODELO DE PRECIOS — CUENTA CATL VÍA CAVEX
A2: Editar SOLO las celdas amarillas. El azul es un dato de entrada; el negro se calcula solo.
A4: LEYENDA | B4: Celda a editar | C4: Dato de entrada | D4: Calculado | E4: De otra hoja
A6: MACRO — CHILE, AGOSTO 2026
A7: Tipo de cambio (CLP por USD) | B7: 915 | F7: Rango observado 909–928 en agosto 2026 (Wise)
A8: Jornada laboral máxima (horas/semana) | B8: 42 | F8: Ley 21.561, vigente desde el 26 de abril de 2026
A9: Ingreso mínimo mensual (CLP) | B9: 553553 | F9: Vigente desde mayo 2026
A10: IVA | B10: 0.19 | F10: Los precios de este modelo son netos, sin IVA
A12: CARTERA — LO QUE HAY QUE CONFIRMAR CON CAVEX
A13: Número de sitios en el alcance | B13: 12 | F13: SUPUESTO. Cavex no ha confirmado cómo se reparten los ~6 GW
A14: Potencia media por sitio (MW) | B14: 250 | F14: SUPUESTO. Cambiar cuando Cavex entregue el listado
A15: Planta actual bajo contrato (MW) | B15: 1000 | F15: Contrato vigente Cavex–Quorelia
A17: PRECIO ACTUAL DEL CONTRATO VIGENTE
A18: Tarifa mensual actual (CLP, neta) | B18: 300000 | F18: Lo que Quorelia factura hoy a Cavex por 1 GW
A20: COSTOS — ESCENARIO A · SOLO CAPA DE DATOS (puntos 1, 2 parcial y 5)
A21: Guardia técnica 24/7 — 4 ingenieros en rotación | B21: 3400000 | F21: Bono de disponibilidad + horas efectivas de intervención
A22: Analista de operaciones (1 FTE cargado) | B22: 2200000 | F22: Revisa hallazgos, emite informes, atiende a Cavex
A23: Jefatura técnica / QA (0,5 FTE) | B23: 1500000 | F23: Control de calidad de la cifra publicada
A24: Infraestructura (hosting, ingesta, almacenamiento) | B24: 1200000 | F24: Redundancia incluida
A25: Licencias y herramientas (alerting, ticketing) | B25: 600000
A26: Seguro de responsabilidad civil profesional (E&O) | B26: 800000 | F26: NUEVO — obligatorio si se asume alcance 24/7
A27: Overhead administrativo y comercial | B27: 0.2
A28: COSTO FIJO MENSUAL — ESCENARIO A | B28: =SUM(B21:B26)*(1+B27) -> 11640000
A29: Costo marginal por sitio adicional | B29: 200000 | F29: Ingesta, almacenamiento y tiempo de analista por hallazgo
A31: COSTOS — ESCENARIO B · CENTRO 24/7 CON DOTACIÓN (los 5 puntos del correo)
A32: Puestos concurrentes 24/7 | B32: 2 | F32: Uno solo no cubre alarmas + llamadas + órdenes a la vez
A33: Holgura por vacaciones, licencias y capacitación | B33: 0.15 | F33: 15 días hábiles de vacaciones + licencias + formación
A34: FTE necesarios por puesto 24/7 | B34: =168/B8*(1+B33) -> 4.6 | F34: 168 horas semanales ÷ jornada legal, más la holgura
A35: Costo cargado por operador de turno (CLP/mes) | B35: 1600000 | F35: Bruto + turnos rotativos nocturnos + cargas del empleador
A36: Ingenieros senior / jefes de turno | B36: 3
A37: Costo cargado por senior (CLP/mes) | B37: 2600000
A38: Telefonía y atención multilingüe (ES/PT/EN/ZH) | B38: 1500000 | F38: Punto 4 del correo: atención de llamadas 24/7
A39: Infraestructura y licencias del centro | B39: 2100000
A40: Seguro RC ampliado (juicio operacional sobre alarmas BMS) | B40: 1800000 | F40: Punto 2: «preliminary judgments» sobre baterías de litio
A41: COSTO FIJO MENSUAL — ESCENARIO B | B41: =(ROUND(B32*B34,0)*B35+B36*B37+B38+B39+B40)*(1+B27) -> 33120000
A42: Costo marginal por sitio adicional (escenario B) | B42: 300000

Sheet Precio actual vs mercado
A1: DÓNDE ESTÁ EL PRECIO ACTUAL
A2: Normalización del contrato vigente y comparación contra la tabla de referencia del propio Quorelia.
A4: Métrica | B4: Valor | C4: Unidad | D4: Cómo se calcula
A5: Tarifa mensual actual | B5: =Supuestos!B18 -> 300000 | C5: CLP/mes | D5: Contrato vigente Cavex–Quorelia
A6: Tarifa mensual actual en dólares | B6: =Supuestos!B18/Supuestos!B7 -> 327.86885 | C6: USD/mes | D6: ÷ tipo de cambio
A7: Ingreso anual del contrato | B7: =Supuestos!B18*12 -> 3600000 | C7: CLP/año | D7: × 12
A8: Ingreso anual en dólares | B8: =Supuestos!B18*12/Supuestos!B7 -> 3934.4262 | C8: USD/año
A9: Precio por MW | B9: =Supuestos!B18/Supuestos!B15 -> 300 | C9: CLP/MW/mes | D9: ÷ 1.000 MW contratados
A10: Precio por MW al año | B10: =Supuestos!B18*12/Supuestos!B15/Supuestos!B7 -> 3.9344262 | C10: USD/MW/año
A11: Como fracción de UN sueldo mínimo | B11: =Supuestos!B18/Supuestos!B9 -> 0.54195353 | C11: × IMM | D11: El ingreso mensual completo de esta cuenta
A13: CONTRA LA TABLA DE REFERENCIA QUE YA TENÍAS
A14: Proveedor | B14: Piso indicativo (USD/año) | C14: Quorelia hoy | D14: Cuántas veces más caro es el piso
A15: Quorelia · objetivo propio | B15: 20000 | C15: =Supuestos!B18*12/Supuestos!B7/B15 -> 0.19672131 | D15: =B15/(Supuestos!B18*12/Supuestos!B7) -> 5.0833333
A16: AVEVA PI System | B16: 25000 | C16: =Supuestos!B18*12/Supuestos!B7/B16 -> 0.15737705 | D16: =B16/(Supuestos!B18*12/Supuestos!B7) -> 6.3541667
A17: AlsoEnergy | B17: 30000 | C17: =Supuestos!B18*12/Supuestos!B7/B17 -> 0.13114754 | D17: =B17/(Supuestos!B18*12/Supuestos!B7) -> 7.625
A18: Power Factors / Unity | B18: 50000 | C18: =Supuestos!B18*12/Supuestos!B7/B18 -> 0.078688525 | D18: =B18/(Supuestos!B18*12/Supuestos!B7) -> 12.708333
A19: ABB | B19: 75000 | C19: =Supuestos!B18*12/Supuestos!B7/B19 -> 0.052459016 | D19: =B19/(Supuestos!B18*12/Supuestos!B7) -> 19.0625
A20: Siemens · Hitachi · GE Vernova | B20: 100000 | C20: =Supuestos!B18*12/Supuestos!B7/B20 -> 0.039344262 | D20: =B20/(Supuestos!B18*12/Supuestos!B7) -> 25.416667
A22: LO QUE ESTABAS PENSANDO COBRAR
A23: Tarifa propuesta (CLP/sitio/mes) | B23: USD/sitio/año | C23: % de tu propio piso de US$20.000
A24: 500000 | B24: =A24*12/Supuestos!B7 -> 6557.377 | C24: =B24/B15 -> 0.32786885
A25: 1000000 | B25: =A25*12/Supuestos!B7 -> 13114.754 | C25: =B25/B15 -> 0.6557377
A27: Incluso el techo de tu rango (1.000.000 CLP/sitio/mes) queda por debajo del piso de tu propia tabla de referencia.

Sheet Tarifa recomendada
A1: TARIFA RECOMENDADA — TRES BLOQUES
A2: Separar la plataforma (escala) del servicio 24/7 (no escala). Amarillo = editable.
A4: BLOQUE 1 · Plataforma, verificación y reportería — recurrente por sitio
A5: Banda de potencia | B5: CLP/sitio/mes | C5: USD/sitio/mes | D5: USD/sitio/año
A6: Hasta 200 MW | B6: 950000 | C6: =B6/Supuestos!B7 -> 1038.2514 | D6: =B6*12/Supuestos!B7 -> 12459.016
A7: 200 – 500 MW | B7: 1450000 | C7: =B7/Supuestos!B7 -> 1584.6995 | D7: =B7*12/Supuestos!B7 -> 19016.393
A8: Más de 500 MW | B8: 1950000 | C8: =B8/Supuestos!B7 -> 2131.1475 | D8: =B8*12/Supuestos!B7 -> 25573.77
A10: BLOQUE 2 · Servicio de monitoreo y guardia 24/7 — cargo fijo de cuenta
A11: Cargo fijo mensual (hasta 20 sitios) | B11: 14500000 | C11: =B11/Supuestos!B7 -> 15846.995
A12: Incremento por sitio a partir del 21º | B12: 350000
A14: BLOQUE 3 · Implementación — pago único por sitio
A15: Tipo de integración | B15: CLP (una vez) | C15: USD
A16: Estándar — SCADA/EMS conocido | B16: 6500000 | C16: =B16/Supuestos!B7 -> 7103.8251
A17: Compleja — BMS propietario o multi-vendor | B17: 13000000 | C17: =B17/Supuestos!B7 -> 14207.65
A19: CÓMO QUEDA SEGÚN EL TAMAÑO DE LA CARTERA — escenario A (solo capa de datos)
A20: Sitios en cartera | B20: Recurrente CLP/mes | C20: USD/año | D20: USD/sitio/año | E20: Costo CLP/mes | F20: Resultado CLP/mes | G20: Margen bruto
A21: 1 | B21: =A21*B8+B11+MAX(0,A21-20)*B12 -> 16450000 | C21: =B21*12/Supuestos!B7 -> 215737.7 | D21: =C21/A21 -> 215737.7 | E21: =Supuestos!B28+A21*Supuestos!B29 -> 11840000 | F21: =B21-E21 -> 4610000 | G21: =IF(B21=0,0,F21/B21) -> 0.28024316
A22: 6 | B22: =A22*B7+B11+MAX(0,A22-20)*B12 -> 23200000 | C22: =B22*12/Supuestos!B7 -> 304262.3 | D22: =C22/A22 -> 50710.383 | E22: =Supuestos!B28+A22*Supuestos!B29 -> 12840000 | F22: =B22-E22 -> 10360000 | G22: =IF(B22=0,0,F22/B22) -> 0.44655172
A23: 12 | B23: =A23*B7+B11+MAX(0,A23-20)*B12 -> 31900000 | C23: =B23*12/Supuestos!B7 -> 418360.66 | D23: =C23/A23 -> 34863.388 | E23: =Supuestos!B28+A23*Supuestos!B29 -> 14040000 | F23: =B23-E23 -> 17860000 | G23: =IF(B23=0,0,F23/B23) -> 0.55987461
A24: 20 | B24: =A24*B7+B11+MAX(0,A24-20)*B12 -> 43500000 | C24: =B24*12/Supuestos!B7 -> 570491.8 | D24: =C24/A24 -> 28524.59 | E24: =Supuestos!B28+A24*Supuestos!B29 -> 15640000 | F24: =B24-E24 -> 27860000 | G24: =IF(B24=0,0,F24/B24) -> 0.64045977
A25: 30 | B25: =A25*B6+B11+MAX(0,A25-20)*B12 -> 46500000 | C25: =B25*12/Supuestos!B7 -> 609836.07 | D25: =C25/A25 -> 20327.869 | E25: =Supuestos!B28+A25*Supuestos!B29 -> 17640000 | F25: =B25-E25 -> 28860000 | G25: =IF(B25=0,0,F25/B25) -> 0.62064516
A26: 40 | B26: =A26*B6+B11+MAX(0,A26-20)*B12 -> 59500000 | C26: =B26*12/Supuestos!B7 -> 780327.87 | D26: =C26/A26 -> 19508.197 | E26: =Supuestos!B28+A26*Supuestos!B29 -> 19640000 | F26: =B26-E26 -> 39860000 | G26: =IF(B26=0,0,F26/B26) -> 0.66991597

Sheet Escenario A vs B
A1: QUÉ PASA SI ACEPTAS LOS CINCO PUNTOS DEL CORREO
A2: Escenario A = capa de datos (1, 2 parcial, 5). Escenario B = centro 24/7 con dotación (los 5).
A4: Punto del correo de CATL | B4: Naturaleza | C4: ¿Quorelia o Cavex? | D4: Por qué
A5: 1 · Monitoreo en tiempo real 24/7 de BMS, PCS y EMS | B5: Software | C5: QUORELIA | D5: Es exactamente el producto. Costo marginal casi nulo.
A6: 2 · Manejo de alarmas: detectar, clasificar, notificar, registrar | B6: Software | C6: QUORELIA | D6: La detección y el registro trazable son el diferenciador.
A7: 2b · «Preliminary judgments» sobre la alarma | B7: Decisión operacional | C7: CAVEX | D7: Juicio sobre baterías de litio. Contradice tus Términos §03.
A8: 3 · Órdenes de trabajo: distribuir y gestionar 24/7 | B8: Coordinación de terreno | C8: CAVEX | D8: Trabajo humano de campo. Quorelia puede generar el hallazgo, no despachar cuadrillas.
A9: 4 · Atención de llamadas 24/7 a cliente y personal en sitio | B9: Call center | C9: CAVEX | D9: Es un call center multilingüe. Margen bajo, nada que ver con tu producto.
A10: 5 · Registro de datos e informe diario de operación | B10: Software | C10: QUORELIA | D10: Ya lo entregas hoy. Es el corazón del servicio.
A12: Comparación | B12: Escenario A · capa de datos | C12: Escenario B · centro dotado | D12: Diferencia
A13: Costo fijo mensual (CLP) | B13: =Supuestos!B28 -> 11640000 | C13: =Supuestos!B41 -> 33120000 | D13: =C13-B13 -> 21480000
A14: Costo fijo anual (CLP) | B14: =B13*12 -> 139680000 | C14: =C13*12 -> 397440000 | D14: =C14-B14 -> 257760000
A15: Costo fijo anual (USD) | B15: =B13*12/Supuestos!B7 -> 152655.74 | C15: =C13*12/Supuestos!B7 -> 434360.66 | D15: =C15-B15 -> 281704.92
A16: Personas en nómina dedicadas | B16: =5.5 -> 5.5 | C16: =ROUND(Supuestos!B32*Supuestos!B34,0)+Supuestos!B36 -> 12 | D16: =C16-B16 -> 6.5
A17: Sitios para equilibrio a 1.000.000 CLP/sitio/mes | B17: =ROUNDUP(Supuestos!B28/(1000000-Supuestos!B29),0) -> 15 | C17: =ROUNDUP(Supuestos!B41/(1000000-Supuestos!B42),0) -> 48 | D17: =C17-B17 -> 33
A18: Sitios para equilibrio a 500.000 CLP/sitio/mes | B18: =ROUNDUP(Supuestos!B28/(500000-Supuestos!B29),0) -> 39 | C18: =ROUNDUP(Supuestos!B41/(500000-Supuestos!B42),0) -> 166 | D18: =C18-B18 -> 127
A20: El escenario B no es una ampliación del servicio: es otro negocio, con costo laboral que no escala y margen de BPO.
A22: QUÉ PASA CON LO QUE IBAS A COTIZAR — cartera de 12 sitios
A23: Opción de precio | B23: Ingreso CLP/mes | C23: Costo CLP/mes | D23: Resultado CLP/mes | E23: Margen
A24: Tu rango bajo — 500.000 CLP/sitio | B24: =12*500000 -> 6000000 | C24: =Supuestos!B28+12*Supuestos!B29 -> 14040000 | D24: =B24-C24 -> -8040000 | E24: =D24/B24 -> -1.34
A25: Tu rango alto — 1.000.000 CLP/sitio | B25: =12*1000000 -> 12000000 | C25: =Supuestos!B28+12*Supuestos!B29 -> 14040000 | D25: =B25-C25 -> -2040000 | E25: =D25/B25 -> -0.17
A26: Tarifa recomendada (bloques 1+2) | B26: =12*'Tarifa recomendada'!B7+'Tarifa recomendada'!B11 -> 31900000 | C26: =Supuestos!B28+12*Supuestos!B29 -> 14040000 | D26: =B26-C26 -> 17860000 | E26: =D26/B26 -> 0.55987461
